setup.py
introspeqt/__init__.py
introspeqt.egg-info/PKG-INFO
introspeqt.egg-info/SOURCES.txt
introspeqt.egg-info/dependency_links.txt
introspeqt.egg-info/requires.txt
introspeqt.egg-info/top_level.txt