Metadata-Version: 1.0
Name: introspeqt
Version: 0.0.2
Summary: Simple introspector for PySide applications.
Home-page: https://github.com/davidmartinezanim/introspeqt
Author: David Martinez
Author-email: david.martinez.anim@gmail.com
License: UNKNOWN
Platform: UNKNOWN
